moralis_streams_client/__init__.py
moralis_streams_client/__main__.py
moralis_streams_client/api.py
moralis_streams_client/app.py
moralis_streams_client/auth.py
moralis_streams_client/cli.py
moralis_streams_client/content_size_limit.py
moralis_streams_client/defaults.py
moralis_streams_client/event_queue.py
moralis_streams_client/exception_handler.py
moralis_streams_client/exceptions.py
moralis_streams_client/logconfig.py
moralis_streams_client/server.py
moralis_streams_client/settings.py
moralis_streams_client/signature.py
moralis_streams_client/tunnel.py
moralis_streams_client/validate.py
moralis_streams_client/version.py
moralis_streams_client/webhook.py
moralis_streams_client/webhook_cli.py
moralis_streams_client/models/Partial_streamsTypes.py
moralis_streams_client/models/__init__.py
moralis_streams_client/models/addressesTypes.py
moralis_streams_client/models/historyTypes.py
moralis_streams_client/models/model.py
moralis_streams_client/models/settingsTypes.py
moralis_streams_client/models/statsTypes.py
moralis_streams_client/models/streamTypes.py
moralis_streams_client/models/streamsTypes.py
moralis_streams_client/models/webhookTypes.py
moralis_streams_client-0.6.4.dist-info/entry_points.txt
moralis_streams_client-0.6.4.dist-info/LICENSE
moralis_streams_client-0.6.4.dist-info/WHEEL
moralis_streams_client-0.6.4.dist-info/METADATA
moralis_streams_client-0.6.4.dist-info/RECORD
