Metadata-Version: 2.1
Name: moralis-streams-client
Version: 0.6.4
Summary: Client module for the Moralis Streams API, including a CLI and a webhook utility for buffering and forwarding endpoint callbacks.
Keywords: moralis_streams_client
Author-email: Matt Krueger <mkrueger@rstms.net>
Classifier: Intended Audience :: Developers
Classifier: Natural Language :: English
Classifier: Programming Language :: Python :: 3
Classifier: Programming Language :: Python :: 3.10
Requires-Dist: asgi-logger
Requires-Dist: asyncclick
Requires-Dist: pycryptodome
Requires-Dist: eth-utils
Requires-Dist: FastAPI
Requires-Dist: orjson
Requires-Dist: psutil
Requires-Dist: pydantic
Requires-Dist: pyngrok
Requires-Dist: httpx
Requires-Dist: starlette
Requires-Dist: toml
Requires-Dist: uvicorn
Requires-Dist: ape-apeman==0.1.22 ; extra == "dev"
Requires-Dist: backoff ; extra == "dev"
Requires-Dist: black ; extra == "dev"
Requires-Dist: bump2version ; extra == "dev"
Requires-Dist: coverage ; extra == "dev"
Requires-Dist: eth-account ; extra == "dev"
Requires-Dist: MoralisSDK ; extra == "dev"
Requires-Dist: flake8 ; extra == "dev"
Requires-Dist: flake8-length ; extra == "dev"
Requires-Dist: httpx ; extra == "dev"
Requires-Dist: isort ; extra == "dev"
Requires-Dist: pdbpp ; extra == "dev"
Requires-Dist: pytest ; extra == "dev"
Requires-Dist: pytest-asyncio ; extra == "dev"
Requires-Dist: pytest-datadir ; extra == "dev"
Requires-Dist: python-box ; extra == "dev"
Requires-Dist: ratelimit ; extra == "dev"
Requires-Dist: tox ; extra == "dev"
Requires-Dist: m2r2 ; extra == "docs"
Requires-Dist: sphinx ; extra == "docs"
Requires-Dist: sphinx-click ; extra == "docs"
Requires-Dist: sphinx-rtd-theme ; extra == "docs"
Project-URL: Home, https://github.com/rstms/moralis_streams_client
Provides-Extra: dev
Provides-Extra: docs
